Flask_PyOTP-0.0.1.dist-info/DESCRIPTION.rst
Flask_PyOTP-0.0.1.dist-info/METADATA
Flask_PyOTP-0.0.1.dist-info/RECORD
Flask_PyOTP-0.0.1.dist-info/WHEEL
Flask_PyOTP-0.0.1.dist-info/metadata.json
Flask_PyOTP-0.0.1.dist-info/top_level.txt
flask_pyotp/__init__.py
