Metadata-Version: 2.0
Name: Flask-PyOTP
Version: 0.0.1
Summary: PyOTP warpper for flask.
Home-page: https://github.com/TornikeNatsvlishvili/flask-pyotp
Author: Tornike Natsvlishvili
Author-email: tornikenatsvlishvilideveloper@gmail.com
License: MIT
Keywords: otp mfa flask pyotp
Platform: any
Classifier: Intended Audience :: Developers
Classifier: Development Status :: 3 - Alpha
Classifier: License :: OSI Approved :: MIT License
Classifier: Operating System :: OS Independent
Classifier: Environment :: Web Environment
Classifier: Topic :: Security
Classifier: Topic :: Software Development :: Libraries :: Python Modules
Classifier: Programming Language :: Python
Classifier: Programming Language :: Python :: 3
Classifier: Programming Language :: Python :: 3.3
Classifier: Programming Language :: Python :: 3.4
Classifier: Programming Language :: Python :: 3.5
Classifier: Programming Language :: Python :: 3.6
Requires-Dist: Flask (>=0.10)
Requires-Dist: pyotp
